{
   "REPOSITORYNAME" : "robotframework-testsuitesmanagement",
   "PACKAGENAME" : "RobotFramework_TestsuitesManagement",
   "AUTHOR" : "Mai Dinh Nam Son",
   "AUTHOREMAIL" : "son.maidinhnam@vn.bosch.com",
   "DESCRIPTION" : "Functionality to manage RobotFramework testsuites",
   "LONGDESCRIPTIONCONTENTTYPE" : "text/markdown",
   "URL" : "https://github.com/test-fullautomation/robotframework-testsuitesmanagement",
   "PROGRAMMINGLANGUAGE" : "Programming Language :: Python :: 3",
   "LICENCE" : "License :: OSI Approved :: Apache Software License",
   "OPERATINGSYSTEM" : "Operating System :: OS Independent",
   "PYTHONREQUIRES" : ">=3.0",
   "DEVELOPMENTSTATUS" : "Development Status :: 4 - Beta",
   "INTENDEDAUDIENCE" : "Intended Audience :: Developers",
   "TOPIC" : "Topic :: Software Development",
   "INSTALLREQUIRES" : ["pypandoc","colorama","GenPackageDoc","PythonExtensionsCollection"],
   "PACKAGEDATA" : ["*.pdf","./Config/*.json"],
   "PACKAGEDOC" : "./packagedoc",
   "CONSOLESCRIPTS" : ["robfwaio_version = RobotFramework_TestsuitesManagement.version:robfwaio_version"]
}
